checker/__init__.py
checker/fetch_and_prepare.py
checker/huge_dict.py
checker/log_setup.py
checker/main.py
checker/smaller_dict.py
domain_check-1.0.1.dist-info/LICENSE
domain_check-1.0.1.dist-info/METADATA
domain_check-1.0.1.dist-info/WHEEL
domain_check-1.0.1.dist-info/entry_points.txt
domain_check-1.0.1.dist-info/top_level.txt
domain_check-1.0.1.dist-info/RECORD
