Metadata-Version: 2.1
Name: domain-check
Version: 1.0.1
Summary: Check which TLDs are still free for a given name
Home-page: https://github.com/nonchris/check-domain/
Author: nonchris
Author-email: info@nonchris.eu
License: UNKNOWN
Project-URL: Bug Reports, https://github.com/nonchris/domain-check/issues
Project-URL: Source, https://github.com/nonchris/domain-check/
Keywords: domain,tld,check,free
Platform: UNKNOWN
Classifier: Development Status :: 5 - Production/Stable
Classifier: Environment :: Console
Classifier: Intended Audience :: Other Audience
Classifier: Topic :: Internet
Classifier: Typing :: Typed
Classifier: License :: OSI Approved :: GNU General Public License v3 (GPLv3)
Classifier: Programming Language :: Python :: 3
Classifier: Programming Language :: Python :: 3.8
Classifier: Programming Language :: Python :: 3.9
Classifier: Programming Language :: Python :: 3 :: Only
Requires-Python: >=3.8, <4
License-File: LICENSE
Requires-Dist: requests
